Metadata-Version: 1.1
Name: impulsare-ruler
Version: 0.1a4
Summary: Reads records from a queue (put there by reader) and process records
Home-page: https://github.com/impulsare/ruler
Author: Emmanuel Dyan
Author-email: emmanuel@impulsare.io
License: AGPLv3
Download-URL: https://github.com/impulsare/ruler/tarball/0.1a4
Keywords: redis,queue,transform,python,impulsare
Platform: UNKNOWN
Classifier: Development Status :: 3 - Alpha
Classifier: Intended Audience :: Developers
Classifier: Intended Audience :: Information Technology
Classifier: Intended Audience :: Science/Research
Classifier: Intended Audience :: System Administrators
Classifier: License :: OSI Approved :: GNU Affero General Public License v3 or later (AGPLv3+)
Classifier: Programming Language :: Python :: 3.3
Classifier: Programming Language :: Python :: 3.4
Classifier: Programming Language :: Python :: 3.5
Classifier: Programming Language :: Python :: 3.6
Classifier: Topic :: Scientific/Engineering
Classifier: Topic :: System :: Distributed Computing
Classifier: Topic :: System :: Systems Administration
